LICENSE
MANIFEST.in
README.rst
setup.py
PyInvoice.egg-info/PKG-INFO
PyInvoice.egg-info/SOURCES.txt
PyInvoice.egg-info/dependency_links.txt
PyInvoice.egg-info/requires.txt
PyInvoice.egg-info/top_level.txt
pyinvoice/__init__.py
pyinvoice/components.py
pyinvoice/models.py
pyinvoice/templates.py
tests/__init__.py
tests/test_templates.py